seiai/__init__.py
seiai-0.0.1.dist-info/METADATA
seiai-0.0.1.dist-info/WHEEL
seiai-0.0.1.dist-info/top_level.txt
seiai-0.0.1.dist-info/RECORD
