Metadata-Version: 2.1
Name: seiai
Version: 0.0.1
Summary: The Future Of AI On Sei
Author: Teck
Author-email: Teck <Teckdegen@gmail.com>
License: MIT
Keywords: blockchain,sei,ai,defi,chatbot,p2p,tokens
Classifier: Programming Language :: Python :: 3
Classifier: Programming Language :: Python :: 3.8
Classifier: Programming Language :: Python :: 3.9
Classifier: Programming Language :: Python :: 3.10
Classifier: Programming Language :: Python :: 3.11
Classifier: Operating System :: OS Independent
Classifier: Intended Audience :: Developers
Classifier: Topic :: Software Development :: Libraries :: Python Modules
Classifier: Topic :: Internet
Requires-Python: >=3.8
Requires-Dist: aiohttp>=3.10.5
Requires-Dist: cosmpy>=0.8.0
Requires-Dist: langchain>=0.3.0
Requires-Dist: langchain-openai>=0.2.1
Requires-Dist: langchain-anthropic>=0.2.1
Requires-Dist: langchain-google-genai>=0.1.1
Requires-Dist: langchain-groq>=0.2.1
Requires-Dist: mnemonic>=0.20
Provides-Extra: dev
Requires-Dist: pytest>=7.4.0; extra == "dev"
